gldm/__init__.py
gldm/distribution_learning.py
gldm/main.py
gldm/sample_MoLeR.py
gldm/autoencoder/__init__.py
gldm/autoencoder/aae.py
gldm/autoencoder/dataset.py
gldm/autoencoder/decoder.py
gldm/autoencoder/decoding_utils.py
gldm/autoencoder/encoder.py
gldm/autoencoder/model.py
gldm/autoencoder/model_utils.py
gldm/autoencoder/train_guacamol.py
gldm/autoencoder/train_l1000.py
gldm/autoencoder/utils.py
gldm/latent_diffusion/DDIM.py
gldm/latent_diffusion/__init__.py
gldm/latent_diffusion/evaluate_ldm_l1000_metrics.py
gldm/latent_diffusion/evaluation_utils.py
gldm/latent_diffusion/l1000_evaluation_utils.py
gldm/latent_diffusion/moler_ldm.py
gldm/latent_diffusion/sample_GLDM.py
gldm/latent_diffusion/train_ldm_guacamol.py
gldm/latent_diffusion/train_ldm_l1000.py
gldm/latent_diffusion/ldm/__init__.py
gldm/latent_diffusion/ldm/lr_scheduler.py
gldm/latent_diffusion/ldm/util.py
gldm/latent_diffusion/ldm/data/__init__.py
gldm/latent_diffusion/ldm/data/base.py
gldm/latent_diffusion/ldm/data/imagenet.py
gldm/latent_diffusion/ldm/data/lsun.py
gldm/latent_diffusion/ldm/models/__init__.py
gldm/latent_diffusion/ldm/models/autoencoder.py
gldm/latent_diffusion/ldm/models/diffusion/__init__.py
gldm/latent_diffusion/ldm/models/diffusion/classifier.py
gldm/latent_diffusion/ldm/models/diffusion/ddim.py
gldm/latent_diffusion/ldm/models/diffusion/ddpm.py
gldm/latent_diffusion/ldm/models/diffusion/plms.py
gldm/latent_diffusion/ldm/modules/__init__.py
gldm/latent_diffusion/ldm/modules/attention.py
gldm/latent_diffusion/ldm/modules/ema.py
gldm/latent_diffusion/ldm/modules/x_transformer.py
gldm/latent_diffusion/ldm/modules/diffusionmodules/__init__.py
gldm/latent_diffusion/ldm/modules/diffusionmodules/model.py
gldm/latent_diffusion/ldm/modules/diffusionmodules/openaimodel.py
gldm/latent_diffusion/ldm/modules/diffusionmodules/util.py
gldm/latent_diffusion/ldm/modules/distributions/__init__.py
gldm/latent_diffusion/ldm/modules/distributions/distributions.py
gldm-0.2.dist-info/LICENSE
gldm-0.2.dist-info/METADATA
gldm-0.2.dist-info/WHEEL
gldm-0.2.dist-info/top_level.txt
gldm-0.2.dist-info/RECORD
