Metadata-Version: 2.1
Name: gldm
Version: 0.2
License-File: LICENSE
Requires-Dist: torch
Requires-Dist: torch-geometric
Requires-Dist: omegaconf
Requires-Dist: pandas
Requires-Dist: pytorch-lightning
Requires-Dist: tqdm
Requires-Dist: rdkit
Requires-Dist: tensorflow
Requires-Dist: tensorboard
Requires-Dist: einops
